{
   "Name": "Microsoft",
   "url": "https://www.microsoft.com/en-us/",
   "Value": "5000",
   "Logo": "/images/sponsor_logo/microsoft.jpg"
}
{
   "Name": "The Factory",
   "url": "https://www.microsoft.com/en-us/",
   "Value": "5000",
   "Logo": ""
}
{
   "Name": "Hootsuite",
   "url": "https://www.microsoft.com/en-us/",
   "Value": "5000",
   "Logo": ""
}
{
   "Name": "Meetup",
   "url": "https://www.microsoft.com/en-us/",
   "Value": "5000",
   "Logo": ""
}
{
   "Name": "Slack",
   "url": "https://www.microsoft.com/en-us/",
   "Value": "5000",
   "Logo": ""
}
{
   "Name": "Google",
   "url": "https://www.microsoft.com/en-us/",
   "Value": "5000",
   "Logo": "/images/sponsor_logo/google.png"
}
{
   "Name": "Bugsnag",
   "url": "https://www.microsoft.com/en-us/",
   "Value": "5000",
   "Logo": ""
}
{
   "Name": "Adobe",
   "url": "https://www.microsoft.com/en-us/",
   "Value": "5000",
   "Logo": ""
}
{
   "Name": "Intuit",
   "url": "https://www.microsoft.com/en-us/",
   "Value": "5000",
   "Logo": ""
}
{
   "Name": "Amazon Web Services",
   "url": "https://www.microsoft.com/en-us/",
   "Value": "5000",
   "Logo": ""
}
{
   "Name": "Peppino",
   "url": "https://www.microsoft.com/en-us/",
   "Value": "5000",
   "Logo": ""
}
{
   "Name": "Mailchimp",
   "url": "https://www.microsoft.com/en-us/",
   "Value": "5000",
   "Logo": ""
}
{
   "Name": "Heroku",
   "url": "https://www.microsoft.com/en-us/",
   "Value": "5000",
   "Logo": ""
}
{
   "Name": "Data.World",
   "url": "https://www.microsoft.com/en-us/",
   "Value": "5000",
   "Logo": ""
}
{
   "Name": "Airtable",
   "url": "https://www.microsoft.com/en-us/",
   "Value": "5000",
   "Logo": ""
}
